limpo/__init__.py
limpo/limpo.py
limpo-0.0.3.dist-info/LICENSE.text
limpo-0.0.3.dist-info/METADATA
limpo-0.0.3.dist-info/WHEEL
limpo-0.0.3.dist-info/top_level.txt
limpo-0.0.3.dist-info/RECORD
