Metadata-Version: 2.1
Name: limpo
Version: 0.0.3
Summary: Cleaning Pandas dataframes
Author: Alexander Brück
Keywords: python,data,pandas,data cleaning,data exploration
Classifier: Programming Language :: Python :: 3
Classifier: License :: OSI Approved :: MIT License
License-File: LICENSE.text
